card_game/__init__.py
card_game/cards.py
card_game/game.py
card_game/main.py
card_game/player.py
card_game/print_utils.py
jjc_card_game-0.0.3.dist-info/entry_points.txt
jjc_card_game-0.0.3.dist-info/LICENSE
jjc_card_game-0.0.3.dist-info/WHEEL
jjc_card_game-0.0.3.dist-info/METADATA
jjc_card_game-0.0.3.dist-info/RECORD
