Metadata-Version: 2.1
Name: jjc-card-game
Version: 0.0.3
Summary: A very simple card game
Home-page: https://github.com/jonathanchukinas/card_game
License: UNKNOWN
Author: Jonathan Chukinas
Author-email: chukinas@gmail.com
Requires-Python: >=3.6
Classifier: Development Status :: 4 - Beta
Classifier: License :: OSI Approved :: MIT License
Classifier: Programming Language :: Python :: 3.6
Classifier: Programming Language :: Python :: 3.7
Classifier: Programming Language :: Python :: 3.8
Classifier: Environment :: Console
Classifier: Topic :: Games/Entertainment :: Board Games
Classifier: Intended Audience :: End Users/Desktop
Classifier: Natural Language :: English
Classifier: Operating System :: Microsoft :: Windows :: Windows 10
Classifier: Operating System :: OS Independent
Classifier: Programming Language :: Python :: 3.8
Requires-Dist: click
Requires-Dist: colorama
Requires-Dist: PTable
Requires-Dist: pytest; extra == "test"
Requires-Dist: pytest-cov; extra == "test"
Requires-Dist: tox; extra == "test"
Provides-Extra: test
